marklogic_mcp/__init__.py
marklogic_mcp/server.py
marklogic_mcp-0.1.0.dist-info/licenses/LICENSE
marklogic_mcp-0.1.0.dist-info/METADATA
marklogic_mcp-0.1.0.dist-info/WHEEL
marklogic_mcp-0.1.0.dist-info/top_level.txt
marklogic_mcp-0.1.0.dist-info/RECORD
