Metadata-Version: 2.4
Name: marklogic-mcp
Version: 0.1.0
Summary: A Python-based MCP server for MarkLogic database operations
Author-email: Karthik <karthiknarayan@graphai.ca>
License: MIT
Project-URL: Homepage, https://github.com/karthiknarayankotha/marklogic-mcp
Project-URL: Repository, https://github.com/karthiknarayankotha/marklogic-mcp.git
Project-URL: Documentation, https://github.com/karthiknarayankotha/marklogic-mcp#readme
Project-URL: Bug Tracker, https://github.com/karthiknarayankotha/marklogic-mcp/issues
Keywords: marklogic,database,mcp,server
Classifier: Development Status :: 4 - Beta
Classifier: Intended Audience :: Developers
Classifier: License :: OSI Approved :: MIT License
Classifier: Programming Language :: Python :: 3
Classifier: Programming Language :: Python :: 3.7
Classifier: Programming Language :: Python :: 3.8
Classifier: Programming Language :: Python :: 3.9
Classifier: Programming Language :: Python :: 3.10
Classifier: Programming Language :: Python :: 3.11
Classifier: Programming Language :: Python :: 3.12
Requires-Python: >=3.7
License-File: LICENSE
Requires-Dist: marklogic-python-client>=1.0.0
Requires-Dist: fastmcp>=0.1.0
Requires-Dist: toml>=0.10.2
Requires-Dist: requests>=2.31.0
Requires-Dist: uvicorn>=0.25.0
Dynamic: license-file
